rppc/__init__.py
rppc/_version.py
rppc/cli.py
rppc/templates.py
rppc/utils.py
tests/__init__.py
tests/test_example.py
rppc-0.1.1b3.dist-info/LICENSE
rppc-0.1.1b3.dist-info/METADATA
rppc-0.1.1b3.dist-info/WHEEL
rppc-0.1.1b3.dist-info/entry_points.txt
rppc-0.1.1b3.dist-info/top_level.txt
rppc-0.1.1b3.dist-info/RECORD
