Metadata-Version: 2.1
Name: rppc
Version: 0.1.1b3
Summary: Reproducible Python Package Creator
Home-page: UNKNOWN
Author: ['Landung Setiawan', 'Adrian Prananda']
Author-email: landungs@uw.edu
Maintainer: ['Landung Setiawan', 'Adrian Prananda']
Maintainer-email: landungs@uw.edu
License: MIT
Platform: UNKNOWN
Classifier: Development Status :: 3 - Alpha
Classifier: Intended Audience :: Developers
Classifier: Topic :: Software Development :: Build Tools
Classifier: Operating System :: OS Independent
Classifier: Programming Language :: Python :: 3.6
Classifier: Topic :: Software Development :: Libraries :: Python Modules
Requires-Python: >=3
Requires-Dist: requests
Requires-Dist: versioneer
Requires-Dist: munch
Requires-Dist: sphinx
Requires-Dist: nbsphinx
Requires-Dist: pyyaml
Requires-Dist: doctr
